<?xml version="1.0" encoding="utf-8"?>
<TextureAtlas imagePath="shaggy_red.png">
	<!-- Created with Adobe Animate version 21.0.0.35450 -->
	<!-- http://www.adobe.com/products/animate.html -->
	<SubTexture name="shaggy_down0000" x="5679" y="662" width="437" height="557" frameX="0" frameY="-30" frameWidth="438" frameHeight="587"/>
	<SubTexture name="shaggy_down0001" x="5023" y="665" width="433" height="560" frameX="-3" frameY="-27" frameWidth="438" frameHeight="587"/>
	<SubTexture name="shaggy_down0002" x="4215" y="647" width="431" height="569" frameX="-7" frameY="-18" frameWidth="438" frameHeight="587"/>
	<SubTexture name="shaggy_down0003" x="4215" y="647" width="431" height="569" frameX="-7" frameY="-18" frameWidth="438" frameHeight="587"/>
	<SubTexture name="shaggy_down0004" x="7325" y="10" width="428" height="579" frameX="-10" frameY="-8" frameWidth="438" frameHeight="587"/>
	<SubTexture name="shaggy_down0005" x="7325" y="10" width="428" height="579" frameX="-10" frameY="-8" frameWidth="438" frameHeight="587"/>
	<SubTexture name="shaggy_down0006" x="3775" y="646" width="420" height="586" frameX="-13" frameY="-1" frameWidth="438" frameHeight="587"/>
	<SubTexture name="shaggy_down0007" x="3775" y="646" width="420" height="586" frameX="-13" frameY="-1" frameWidth="438" frameHeight="587"/>
	<SubTexture name="shaggy_down0008" x="7325" y="609" width="420" height="587" frameX="-13" frameY="0" frameWidth="438" frameHeight="587"/>
	<SubTexture name="shaggy_down0009" x="7325" y="609" width="420" height="587" frameX="-13" frameY="0" frameWidth="438" frameHeight="587"/>
	<SubTexture name="shaggy_down0010" x="7325" y="609" width="420" height="587" frameX="-13" frameY="0" frameWidth="438" frameHeight="587"/>
	<SubTexture name="shaggy_down0011" x="7325" y="609" width="420" height="587" frameX="-13" frameY="0" frameWidth="438" frameHeight="587"/>
	<SubTexture name="shaggy_down0012" x="7325" y="609" width="420" height="587" frameX="-13" frameY="0" frameWidth="438" frameHeight="587"/>
	<SubTexture name="shaggy_down0013" x="7325" y="609" width="420" height="587" frameX="-13" frameY="0" frameWidth="438" frameHeight="587"/>
	<SubTexture name="shaggy_down0014" x="7325" y="609" width="420" height="587" frameX="-13" frameY="0" frameWidth="438" frameHeight="587"/>
	<SubTexture name="shaggy_down0015" x="7325" y="609" width="420" height="587" frameX="-13" frameY="0" frameWidth="438" frameHeight="587"/>
	<SubTexture name="shaggy_down0016" x="7325" y="609" width="420" height="587" frameX="-13" frameY="0" frameWidth="438" frameHeight="587"/>
	<SubTexture name="shaggy_down0017" x="7325" y="609" width="420" height="587" frameX="-13" frameY="0" frameWidth="438" frameHeight="587"/>
	<SubTexture name="shaggy_down0018" x="7325" y="609" width="420" height="587" frameX="-13" frameY="0" frameWidth="438" frameHeight="587"/>
	<SubTexture name="shaggy_down0019" x="7325" y="609" width="420" height="587" frameX="-13" frameY="0" frameWidth="438" frameHeight="587"/>
	<SubTexture name="shaggy_down0020" x="7325" y="609" width="420" height="587" frameX="-13" frameY="0" frameWidth="438" frameHeight="587"/>
	<SubTexture name="shaggy_down0021" x="7325" y="609" width="420" height="587" frameX="-13" frameY="0" frameWidth="438" frameHeight="587"/>
	<SubTexture name="shaggy_down0022" x="7325" y="609" width="420" height="587" frameX="-13" frameY="0" frameWidth="438" frameHeight="587"/>
	<SubTexture name="shaggy_down0023" x="7325" y="609" width="420" height="587" frameX="-13" frameY="0" frameWidth="438" frameHeight="587"/>
	<SubTexture name="shaggy_down0024" x="7325" y="609" width="420" height="587" frameX="-13" frameY="0" frameWidth="438" frameHeight="587"/>
	<SubTexture name="shaggy_down0025" x="7325" y="609" width="420" height="587" frameX="-13" frameY="0" frameWidth="438" frameHeight="587"/>
	<SubTexture name="shaggy_down0026" x="7325" y="609" width="420" height="587" frameX="-13" frameY="0" frameWidth="438" frameHeight="587"/>
	<SubTexture name="shaggy_idle0000" x="3394" y="739" width="326" height="701" frameX="0" frameY="-53" frameWidth="354" frameHeight="755"/>
	<SubTexture name="shaggy_idle0001" x="3394" y="739" width="326" height="701" frameX="0" frameY="-53" frameWidth="354" frameHeight="755"/>
	<SubTexture name="shaggy_idle0002" x="5476" y="1239" width="323" height="703" frameX="-5" frameY="-51" frameWidth="354" frameHeight="755"/>
	<SubTexture name="shaggy_idle0003" x="6136" y="665" width="330" height="712" frameX="-7" frameY="-42" frameWidth="354" frameHeight="755"/>
	<SubTexture name="shaggy_idle0004" x="6136" y="665" width="330" height="712" frameX="-7" frameY="-42" frameWidth="354" frameHeight="755"/>
	<SubTexture name="shaggy_idle0005" x="4666" y="653" width="337" height="725" frameX="-12" frameY="-29" frameWidth="354" frameHeight="755"/>
	<SubTexture name="shaggy_idle0006" x="4666" y="653" width="337" height="725" frameX="-12" frameY="-29" frameWidth="354" frameHeight="755"/>
	<SubTexture name="shaggy_idle0007" x="6968" y="10" width="337" height="753" frameX="-15" frameY="-1" frameWidth="354" frameHeight="755"/>
	<SubTexture name="shaggy_idle0008" x="6968" y="10" width="337" height="753" frameX="-15" frameY="-1" frameWidth="354" frameHeight="755"/>
	<SubTexture name="shaggy_idle0009" x="6968" y="10" width="337" height="753" frameX="-15" frameY="-1" frameWidth="354" frameHeight="755"/>
	<SubTexture name="shaggy_idle0010" x="6968" y="10" width="337" height="753" frameX="-15" frameY="-1" frameWidth="354" frameHeight="755"/>
	<SubTexture name="shaggy_idle0011" x="6608" y="10" width="340" height="755" frameX="-14" frameY="0" frameWidth="354" frameHeight="755"/>
	<SubTexture name="shaggy_idle0012" x="6608" y="10" width="340" height="755" frameX="-14" frameY="0" frameWidth="354" frameHeight="755"/>
	<SubTexture name="shaggy_idle0013" x="6608" y="10" width="340" height="755" frameX="-14" frameY="0" frameWidth="354" frameHeight="755"/>
	<SubTexture name="shaggy_idle0014" x="6608" y="10" width="340" height="755" frameX="-14" frameY="0" frameWidth="354" frameHeight="755"/>
	<SubTexture name="shaggy_idle20000" x="4215" y="1236" width="326" height="701" frameX="0" frameY="-53" frameWidth="326" frameHeight="755"/>
	<SubTexture name="shaggy_idle20001" x="4215" y="1236" width="326" height="701" frameX="0" frameY="-53" frameWidth="326" frameHeight="755"/>
	<SubTexture name="shaggy_idle20002" x="10" y="1262" width="320" height="702" frameX="-2" frameY="-52" frameWidth="326" frameHeight="755"/>
	<SubTexture name="shaggy_idle20003" x="3740" y="1252" width="317" height="709" frameX="-3" frameY="-45" frameWidth="326" frameHeight="755"/>
	<SubTexture name="shaggy_idle20004" x="3740" y="1252" width="317" height="709" frameX="-3" frameY="-45" frameWidth="326" frameHeight="755"/>
	<SubTexture name="shaggy_idle20005" x="350" y="1271" width="304" height="724" frameX="-10" frameY="-30" frameWidth="326" frameHeight="755"/>
	<SubTexture name="shaggy_idle20006" x="350" y="1271" width="304" height="724" frameX="-10" frameY="-30" frameWidth="326" frameHeight="755"/>
	<SubTexture name="shaggy_idle20007" x="1602" y="1273" width="292" height="751" frameX="-16" frameY="-3" frameWidth="326" frameHeight="755"/>
	<SubTexture name="shaggy_idle20008" x="1602" y="1273" width="292" height="751" frameX="-16" frameY="-3" frameWidth="326" frameHeight="755"/>
	<SubTexture name="shaggy_idle20009" x="1602" y="1273" width="292" height="751" frameX="-16" frameY="-3" frameWidth="326" frameHeight="755"/>
	<SubTexture name="shaggy_idle20010" x="1602" y="1273" width="292" height="751" frameX="-16" frameY="-3" frameWidth="326" frameHeight="755"/>
	<SubTexture name="shaggy_idle20011" x="1914" y="1273" width="287" height="755" frameX="-19" frameY="0" frameWidth="326" frameHeight="755"/>
	<SubTexture name="shaggy_idle20012" x="1914" y="1273" width="287" height="755" frameX="-19" frameY="0" frameWidth="326" frameHeight="755"/>
	<SubTexture name="shaggy_idle20013" x="1914" y="1273" width="287" height="755" frameX="-19" frameY="0" frameWidth="326" frameHeight="755"/>
	<SubTexture name="shaggy_idle20014" x="1914" y="1273" width="287" height="755" frameX="-19" frameY="0" frameWidth="326" frameHeight="755"/>
	<SubTexture name="shaggy_left0000" x="3775" y="10" width="465" height="616" frameX="0" frameY="-18" frameWidth="465" frameHeight="635"/>
	<SubTexture name="shaggy_left0001" x="4260" y="10" width="462" height="617" frameX="-3" frameY="-17" frameWidth="465" frameHeight="635"/>
	<SubTexture name="shaggy_left0002" x="4742" y="10" width="453" height="623" frameX="-12" frameY="-11" frameWidth="465" frameHeight="635"/>
	<SubTexture name="shaggy_left0003" x="4742" y="10" width="453" height="623" frameX="-12" frameY="-11" frameWidth="465" frameHeight="635"/>
	<SubTexture name="shaggy_left0004" x="5679" y="10" width="446" height="632" frameX="-19" frameY="-3" frameWidth="465" frameHeight="635"/>
	<SubTexture name="shaggy_left0005" x="5679" y="10" width="446" height="632" frameX="-19" frameY="-3" frameWidth="465" frameHeight="635"/>
	<SubTexture name="shaggy_left0006" x="5215" y="10" width="444" height="635" frameX="-21" frameY="0" frameWidth="465" frameHeight="635"/>
	<SubTexture name="shaggy_left0007" x="6145" y="10" width="443" height="635" frameX="-22" frameY="0" frameWidth="465" frameHeight="635"/>
	<SubTexture name="shaggy_left0008" x="6145" y="10" width="443" height="635" frameX="-22" frameY="0" frameWidth="465" frameHeight="635"/>
	<SubTexture name="shaggy_left0009" x="6145" y="10" width="443" height="635" frameX="-22" frameY="0" frameWidth="465" frameHeight="635"/>
	<SubTexture name="shaggy_left0010" x="6145" y="10" width="443" height="635" frameX="-22" frameY="0" frameWidth="465" frameHeight="635"/>
	<SubTexture name="shaggy_left0011" x="6145" y="10" width="443" height="635" frameX="-22" frameY="0" frameWidth="465" frameHeight="635"/>
	<SubTexture name="shaggy_left0012" x="6145" y="10" width="443" height="635" frameX="-22" frameY="0" frameWidth="465" frameHeight="635"/>
	<SubTexture name="shaggy_left0013" x="6145" y="10" width="443" height="635" frameX="-22" frameY="0" frameWidth="465" frameHeight="635"/>
	<SubTexture name="shaggy_left0014" x="6145" y="10" width="443" height="635" frameX="-22" frameY="0" frameWidth="465" frameHeight="635"/>
	<SubTexture name="shaggy_left0015" x="6145" y="10" width="443" height="635" frameX="-22" frameY="0" frameWidth="465" frameHeight="635"/>
	<SubTexture name="shaggy_left0016" x="6145" y="10" width="443" height="635" frameX="-22" frameY="0" frameWidth="465" frameHeight="635"/>
	<SubTexture name="shaggy_left0017" x="6145" y="10" width="443" height="635" frameX="-22" frameY="0" frameWidth="465" frameHeight="635"/>
	<SubTexture name="shaggy_left0018" x="6145" y="10" width="443" height="635" frameX="-22" frameY="0" frameWidth="465" frameHeight="635"/>
	<SubTexture name="shaggy_left0019" x="6145" y="10" width="443" height="635" frameX="-22" frameY="0" frameWidth="465" frameHeight="635"/>
	<SubTexture name="shaggy_left0020" x="6145" y="10" width="443" height="635" frameX="-22" frameY="0" frameWidth="465" frameHeight="635"/>
	<SubTexture name="shaggy_left0021" x="6145" y="10" width="443" height="635" frameX="-22" frameY="0" frameWidth="465" frameHeight="635"/>
	<SubTexture name="shaggy_left0022" x="6145" y="10" width="443" height="635" frameX="-22" frameY="0" frameWidth="465" frameHeight="635"/>
	<SubTexture name="shaggy_left0023" x="6145" y="10" width="443" height="635" frameX="-22" frameY="0" frameWidth="465" frameHeight="635"/>
	<SubTexture name="shaggy_left0024" x="6145" y="10" width="443" height="635" frameX="-22" frameY="0" frameWidth="465" frameHeight="635"/>
	<SubTexture name="shaggy_left0025" x="6145" y="10" width="443" height="635" frameX="-22" frameY="0" frameWidth="465" frameHeight="635"/>
	<SubTexture name="shaggy_left0026" x="6145" y="10" width="443" height="635" frameX="-22" frameY="0" frameWidth="465" frameHeight="635"/>
	<SubTexture name="shaggy_left0027" x="6145" y="10" width="443" height="635" frameX="-22" frameY="0" frameWidth="465" frameHeight="635"/>
	<SubTexture name="shaggy_powerup0000" x="5819" y="1239" width="297" height="755" frameX="0" frameY="-22" frameWidth="297" frameHeight="777"/>
	<SubTexture name="shaggy_powerup0001" x="5819" y="1239" width="297" height="755" frameX="0" frameY="-22" frameWidth="297" frameHeight="777"/>
	<SubTexture name="shaggy_powerup0002" x="2916" y="1269" width="296" height="751" frameX="0" frameY="-20" frameWidth="297" frameHeight="777"/>
	<SubTexture name="shaggy_powerup0003" x="2916" y="1269" width="296" height="751" frameX="0" frameY="-20" frameWidth="297" frameHeight="777"/>
	<SubTexture name="shaggy_powerup0004" x="1296" y="1273" width="286" height="767" frameX="0" frameY="-1" frameWidth="297" frameHeight="777"/>
	<SubTexture name="shaggy_powerup0005" x="1296" y="1273" width="286" height="767" frameX="0" frameY="-1" frameWidth="297" frameHeight="777"/>
	<SubTexture name="shaggy_powerup0006" x="1296" y="1273" width="286" height="767" frameX="0" frameY="-1" frameWidth="297" frameHeight="777"/>
	<SubTexture name="shaggy_powerup0007" x="674" y="1271" width="286" height="768" frameX="0" frameY="0" frameWidth="297" frameHeight="777"/>
	<SubTexture name="shaggy_powerup0008" x="674" y="1271" width="286" height="768" frameX="0" frameY="0" frameWidth="297" frameHeight="777"/>
	<SubTexture name="shaggy_powerup0009" x="674" y="1271" width="286" height="768" frameX="0" frameY="0" frameWidth="297" frameHeight="777"/>
	<SubTexture name="shaggy_powerup0010" x="674" y="1271" width="286" height="768" frameX="0" frameY="0" frameWidth="297" frameHeight="777"/>
	<SubTexture name="shaggy_powerup0011" x="674" y="1271" width="286" height="768" frameX="0" frameY="0" frameWidth="297" frameHeight="777"/>
	<SubTexture name="shaggy_powerup0012" x="674" y="1271" width="286" height="768" frameX="0" frameY="0" frameWidth="297" frameHeight="777"/>
	<SubTexture name="shaggy_powerup0013" x="674" y="1271" width="286" height="768" frameX="0" frameY="0" frameWidth="297" frameHeight="777"/>
	<SubTexture name="shaggy_powerup0014" x="674" y="1271" width="286" height="768" frameX="0" frameY="0" frameWidth="297" frameHeight="777"/>
	<SubTexture name="shaggy_powerup0015" x="674" y="1271" width="286" height="768" frameX="0" frameY="0" frameWidth="297" frameHeight="777"/>
	<SubTexture name="shaggy_powerup0016" x="674" y="1271" width="286" height="768" frameX="0" frameY="0" frameWidth="297" frameHeight="777"/>
	<SubTexture name="shaggy_powerup0017" x="674" y="1271" width="286" height="768" frameX="0" frameY="0" frameWidth="297" frameHeight="777"/>
	<SubTexture name="shaggy_powerup0018" x="674" y="1271" width="286" height="768" frameX="0" frameY="0" frameWidth="297" frameHeight="777"/>
	<SubTexture name="shaggy_powerup0019" x="674" y="1271" width="286" height="768" frameX="0" frameY="0" frameWidth="297" frameHeight="777"/>
	<SubTexture name="shaggy_powerup0020" x="674" y="1271" width="286" height="768" frameX="0" frameY="0" frameWidth="297" frameHeight="777"/>
	<SubTexture name="shaggy_powerup0021" x="674" y="1271" width="286" height="768" frameX="0" frameY="0" frameWidth="297" frameHeight="777"/>
	<SubTexture name="shaggy_powerup0022" x="674" y="1271" width="286" height="768" frameX="0" frameY="0" frameWidth="297" frameHeight="777"/>
	<SubTexture name="shaggy_powerup0023" x="674" y="1271" width="286" height="768" frameX="0" frameY="0" frameWidth="297" frameHeight="777"/>
	<SubTexture name="shaggy_powerup0024" x="674" y="1271" width="286" height="768" frameX="0" frameY="0" frameWidth="297" frameHeight="777"/>
	<SubTexture name="shaggy_powerup0025" x="674" y="1271" width="286" height="768" frameX="0" frameY="0" frameWidth="297" frameHeight="777"/>
	<SubTexture name="shaggy_powerup0026" x="674" y="1271" width="286" height="768" frameX="0" frameY="0" frameWidth="297" frameHeight="777"/>
	<SubTexture name="shaggy_powerup0027" x="674" y="1271" width="286" height="768" frameX="0" frameY="0" frameWidth="297" frameHeight="777"/>
	<SubTexture name="shaggy_powerup0028" x="674" y="1271" width="286" height="768" frameX="0" frameY="0" frameWidth="297" frameHeight="777"/>
	<SubTexture name="shaggy_powerup0029" x="674" y="1271" width="286" height="768" frameX="0" frameY="0" frameWidth="297" frameHeight="777"/>
	<SubTexture name="shaggy_right0000" x="10" y="10" width="479" height="696" frameX="0" frameY="-13" frameWidth="479" frameHeight="709"/>
	<SubTexture name="shaggy_right0001" x="509" y="10" width="479" height="693" frameX="0" frameY="-16" frameWidth="479" frameHeight="709"/>
	<SubTexture name="shaggy_right0002" x="1008" y="10" width="471" height="685" frameX="-2" frameY="-24" frameWidth="479" frameHeight="709"/>
	<SubTexture name="shaggy_right0003" x="1008" y="10" width="471" height="685" frameX="-2" frameY="-24" frameWidth="479" frameHeight="709"/>
	<SubTexture name="shaggy_right0004" x="1962" y="10" width="452" height="681" frameX="-6" frameY="-28" frameWidth="479" frameHeight="709"/>
	<SubTexture name="shaggy_right0005" x="1962" y="10" width="452" height="681" frameX="-6" frameY="-28" frameWidth="479" frameHeight="709"/>
	<SubTexture name="shaggy_right0006" x="1499" y="10" width="443" height="695" frameX="-6" frameY="-14" frameWidth="479" frameHeight="709"/>
	<SubTexture name="shaggy_right0007" x="1499" y="10" width="443" height="695" frameX="-6" frameY="-14" frameWidth="479" frameHeight="709"/>
	<SubTexture name="shaggy_right0008" x="2434" y="10" width="429" height="707" frameX="-12" frameY="-2" frameWidth="479" frameHeight="709"/>
	<SubTexture name="shaggy_right0009" x="2434" y="10" width="429" height="707" frameX="-12" frameY="-2" frameWidth="479" frameHeight="709"/>
	<SubTexture name="shaggy_right0010" x="2883" y="10" width="426" height="709" frameX="-12" frameY="0" frameWidth="479" frameHeight="709"/>
	<SubTexture name="shaggy_right0011" x="3329" y="10" width="426" height="709" frameX="-12" frameY="0" frameWidth="479" frameHeight="709"/>
	<SubTexture name="shaggy_right0012" x="3329" y="10" width="426" height="709" frameX="-12" frameY="0" frameWidth="479" frameHeight="709"/>
	<SubTexture name="shaggy_right0013" x="3329" y="10" width="426" height="709" frameX="-12" frameY="0" frameWidth="479" frameHeight="709"/>
	<SubTexture name="shaggy_right0014" x="3329" y="10" width="426" height="709" frameX="-12" frameY="0" frameWidth="479" frameHeight="709"/>
	<SubTexture name="shaggy_right0015" x="3329" y="10" width="426" height="709" frameX="-12" frameY="0" frameWidth="479" frameHeight="709"/>
	<SubTexture name="shaggy_right0016" x="3329" y="10" width="426" height="709" frameX="-12" frameY="0" frameWidth="479" frameHeight="709"/>
	<SubTexture name="shaggy_right0017" x="3329" y="10" width="426" height="709" frameX="-12" frameY="0" frameWidth="479" frameHeight="709"/>
	<SubTexture name="shaggy_right0018" x="3329" y="10" width="426" height="709" frameX="-12" frameY="0" frameWidth="479" frameHeight="709"/>
	<SubTexture name="shaggy_right0019" x="3329" y="10" width="426" height="709" frameX="-12" frameY="0" frameWidth="479" frameHeight="709"/>
	<SubTexture name="shaggy_right0020" x="3329" y="10" width="426" height="709" frameX="-12" frameY="0" frameWidth="479" frameHeight="709"/>
	<SubTexture name="shaggy_right0021" x="3329" y="10" width="426" height="709" frameX="-12" frameY="0" frameWidth="479" frameHeight="709"/>
	<SubTexture name="shaggy_right0022" x="3329" y="10" width="426" height="709" frameX="-12" frameY="0" frameWidth="479" frameHeight="709"/>
	<SubTexture name="shaggy_right0023" x="3329" y="10" width="426" height="709" frameX="-12" frameY="0" frameWidth="479" frameHeight="709"/>
	<SubTexture name="shaggy_right0024" x="3329" y="10" width="426" height="709" frameX="-12" frameY="0" frameWidth="479" frameHeight="709"/>
	<SubTexture name="shaggy_right0025" x="3329" y="10" width="426" height="709" frameX="-12" frameY="0" frameWidth="479" frameHeight="709"/>
	<SubTexture name="shaggy_right0026" x="3329" y="10" width="426" height="709" frameX="-12" frameY="0" frameWidth="479" frameHeight="709"/>
	<SubTexture name="shaggy_right0027" x="3329" y="10" width="426" height="709" frameX="-12" frameY="0" frameWidth="479" frameHeight="709"/>
	<SubTexture name="shaggy_right0028" x="3329" y="10" width="426" height="709" frameX="-12" frameY="0" frameWidth="479" frameHeight="709"/>
	<SubTexture name="shaggy_right0029" x="3329" y="10" width="426" height="709" frameX="-12" frameY="0" frameWidth="479" frameHeight="709"/>
	<SubTexture name="shaggy_right0030" x="3329" y="10" width="426" height="709" frameX="-12" frameY="0" frameWidth="479" frameHeight="709"/>
	<SubTexture name="shaggy_sit0000" x="509" y="723" width="454" height="528"/>
	<SubTexture name="shaggy_stand0000" x="1486" y="725" width="454" height="528" frameX="-4" frameY="-218" frameWidth="458" frameHeight="754"/>
	<SubTexture name="shaggy_stand0001" x="1486" y="725" width="454" height="528" frameX="-4" frameY="-218" frameWidth="458" frameHeight="754"/>
	<SubTexture name="shaggy_stand0002" x="1008" y="715" width="458" height="528" frameX="0" frameY="-218" frameWidth="458" frameHeight="754"/>
	<SubTexture name="shaggy_stand0003" x="10" y="726" width="458" height="516" frameX="0" frameY="-230" frameWidth="458" frameHeight="754"/>
	<SubTexture name="shaggy_stand0004" x="1960" y="737" width="458" height="516" frameX="0" frameY="-230" frameWidth="458" frameHeight="754"/>
	<SubTexture name="shaggy_stand0005" x="2916" y="739" width="458" height="510" frameX="0" frameY="-236" frameWidth="458" frameHeight="754"/>
	<SubTexture name="shaggy_stand0006" x="6486" y="785" width="458" height="510" frameX="0" frameY="-236" frameWidth="458" frameHeight="754"/>
	<SubTexture name="shaggy_stand0007" x="6964" y="1216" width="458" height="510" frameX="0" frameY="-236" frameWidth="458" frameHeight="754"/>
	<SubTexture name="shaggy_stand0008" x="2438" y="739" width="458" height="516" frameX="0" frameY="-230" frameWidth="458" frameHeight="754"/>
	<SubTexture name="shaggy_stand0009" x="7765" y="780" width="393" height="586" frameX="-20" frameY="-140" frameWidth="458" frameHeight="754"/>
	<SubTexture name="shaggy_stand0010" x="7765" y="780" width="393" height="586" frameX="-20" frameY="-140" frameWidth="458" frameHeight="754"/>
	<SubTexture name="shaggy_stand0011" x="5023" y="1245" width="307" height="739" frameX="-47" frameY="-8" frameWidth="458" frameHeight="754"/>
	<SubTexture name="shaggy_stand0012" x="5023" y="1245" width="307" height="739" frameX="-47" frameY="-8" frameWidth="458" frameHeight="754"/>
	<SubTexture name="shaggy_stand0013" x="7773" y="10" width="330" height="750" frameX="-49" frameY="-4" frameWidth="458" frameHeight="754"/>
	<SubTexture name="shaggy_stand0014" x="7773" y="10" width="330" height="750" frameX="-49" frameY="-4" frameWidth="458" frameHeight="754"/>
	<SubTexture name="shaggy_stand0015" x="6608" y="10" width="340" height="755" frameX="-48" frameY="0" frameWidth="354" frameHeight="755"/>
	<SubTexture name="shaggy_stand0016" x="6608" y="10" width="340" height="755" frameX="-48" frameY="0" frameWidth="354" frameHeight="755"/>
	<SubTexture name="shaggy_stand0017" x="6608" y="10" width="340" height="755" frameX="-48" frameY="0" frameWidth="354" frameHeight="755"/>
	<SubTexture name="shaggy_stand0018" x="6608" y="10" width="340" height="755" frameX="-48" frameY="0" frameWidth="354" frameHeight="755"/>
	<SubTexture name="shaggy_stand0019" x="6608" y="10" width="340" height="755" frameX="-48" frameY="0" frameWidth="354" frameHeight="755"/>
	<SubTexture name="shaggy_stand0020" x="6608" y="10" width="340" height="755" frameX="-48" frameY="0" frameWidth="354" frameHeight="755"/>
	<SubTexture name="shaggy_stand0021" x="6608" y="10" width="340" height="755" frameX="-48" frameY="0" frameWidth="354" frameHeight="755"/>
	<SubTexture name="shaggy_stand0022" x="6608" y="10" width="340" height="755" frameX="-48" frameY="0" frameWidth="354" frameHeight="755"/>
	<SubTexture name="shaggy_stand0023" x="6608" y="10" width="340" height="755" frameX="-48" frameY="0" frameWidth="354" frameHeight="755"/>
	<SubTexture name="shaggy_stand0024" x="6608" y="10" width="340" height="755" frameX="-48" frameY="0" frameWidth="354" frameHeight="755"/>
	<SubTexture name="shaggy_stand0025" x="6608" y="10" width="340" height="755" frameX="-48" frameY="0" frameWidth="354" frameHeight="755"/>
	<SubTexture name="shaggy_stand0026" x="6608" y="10" width="340" height="755" frameX="-48" frameY="0" frameWidth="354" frameHeight="755"/>
	<SubTexture name="shaggy_up0000" x="2519" y="1275" width="275" height="780" frameX="-9" frameY="0" frameWidth="298" frameHeight="780"/>
	<SubTexture name="shaggy_up0001" x="6486" y="1315" width="275" height="778" frameX="-9" frameY="-2" frameWidth="298" frameHeight="780"/>
	<SubTexture name="shaggy_up0002" x="2221" y="1275" width="278" height="772" frameX="-9" frameY="-8" frameWidth="298" frameHeight="780"/>
	<SubTexture name="shaggy_up0003" x="2221" y="1275" width="278" height="772" frameX="-9" frameY="-8" frameWidth="298" frameHeight="780"/>
	<SubTexture name="shaggy_up0004" x="983" y="1263" width="293" height="760" frameX="-3" frameY="-20" frameWidth="298" frameHeight="780"/>
	<SubTexture name="shaggy_up0005" x="983" y="1263" width="293" height="760" frameX="-3" frameY="-20" frameWidth="298" frameHeight="780"/>
	<SubTexture name="shaggy_up0006" x="7442" y="1216" width="298" height="756" frameX="0" frameY="-24" frameWidth="298" frameHeight="780"/>
	<SubTexture name="shaggy_up0007" x="7442" y="1216" width="298" height="756" frameX="0" frameY="-24" frameWidth="298" frameHeight="780"/>
	<SubTexture name="shaggy_up0008" x="7442" y="1216" width="298" height="756" frameX="0" frameY="-24" frameWidth="298" frameHeight="780"/>
	<SubTexture name="shaggy_up0009" x="7442" y="1216" width="298" height="756" frameX="0" frameY="-24" frameWidth="298" frameHeight="780"/>
	<SubTexture name="shaggy_up0010" x="7442" y="1216" width="298" height="756" frameX="0" frameY="-24" frameWidth="298" frameHeight="780"/>
	<SubTexture name="shaggy_up0011" x="7442" y="1216" width="298" height="756" frameX="0" frameY="-24" frameWidth="298" frameHeight="780"/>
	<SubTexture name="shaggy_up0012" x="7442" y="1216" width="298" height="756" frameX="0" frameY="-24" frameWidth="298" frameHeight="780"/>
	<SubTexture name="shaggy_up0013" x="7442" y="1216" width="298" height="756" frameX="0" frameY="-24" frameWidth="298" frameHeight="780"/>
	<SubTexture name="shaggy_up0014" x="7442" y="1216" width="298" height="756" frameX="0" frameY="-24" frameWidth="298" frameHeight="780"/>
	<SubTexture name="shaggy_up0015" x="7442" y="1216" width="298" height="756" frameX="0" frameY="-24" frameWidth="298" frameHeight="780"/>
	<SubTexture name="shaggy_up0016" x="7442" y="1216" width="298" height="756" frameX="0" frameY="-24" frameWidth="298" frameHeight="780"/>
	<SubTexture name="shaggy_up0017" x="7442" y="1216" width="298" height="756" frameX="0" frameY="-24" frameWidth="298" frameHeight="780"/>
	<SubTexture name="shaggy_up0018" x="7442" y="1216" width="298" height="756" frameX="0" frameY="-24" frameWidth="298" frameHeight="780"/>
	<SubTexture name="shaggy_up0019" x="7442" y="1216" width="298" height="756" frameX="0" frameY="-24" frameWidth="298" frameHeight="780"/>
	<SubTexture name="shaggy_up0020" x="7442" y="1216" width="298" height="756" frameX="0" frameY="-24" frameWidth="298" frameHeight="780"/>
	<SubTexture name="shaggy_up0021" x="7442" y="1216" width="298" height="756" frameX="0" frameY="-24" frameWidth="298" frameHeight="780"/>
	<SubTexture name="shaggy_up0022" x="7442" y="1216" width="298" height="756" frameX="0" frameY="-24" frameWidth="298" frameHeight="780"/>
	<SubTexture name="shaggy_up0023" x="7442" y="1216" width="298" height="756" frameX="0" frameY="-24" frameWidth="298" frameHeight="780"/>
	<SubTexture name="shaggy_up0024" x="7442" y="1216" width="298" height="756" frameX="0" frameY="-24" frameWidth="298" frameHeight="780"/>
</TextureAtlas>
